{
	"configurations" : 
	[
		{
			"directories" : 
			[
				{
					"build" : ".",
					"jsonFile" : "directory-.-Release-f5ebdc15457944623624.json",
					"minimumCMakeVersion" : 
					{
						"string" : "3.24"
					},
					"projectIndex" : 0,
					"source" : ".",
					"targetIndexes" : 
					[
						0
					]
				}
			],
			"name" : "Release",
			"projects" : 
			[
				{
					"directoryIndexes" : 
					[
						0
					],
					"name" : "Chitraware",
					"targetIndexes" : 
					[
						0
					]
				}
			],
			"targets" : 
			[
				{
					"directoryIndex" : 0,
					"id" : "Chitraware::@6890427a1f51a3e7e1df",
					"jsonFile" : "target-Chitraware-Release-d9cd7517060a7022100a.json",
					"name" : "Chitraware",
					"projectIndex" : 0
				}
			]
		}
	],
	"kind" : "codemodel",
	"paths" : 
	{
		"build" : "/home/barry/CodeParty/Chitraware/build",
		"source" : "/home/barry/CodeParty/Chitraware"
	},
	"version" : 
	{
		"major" : 2,
		"minor" : 6
	}
}
